README.md
setup.py
dbtlog.egg-info/PKG-INFO
dbtlog.egg-info/SOURCES.txt
dbtlog.egg-info/dependency_links.txt
dbtlog.egg-info/entry_points.txt
dbtlog.egg-info/requires.txt
dbtlog.egg-info/top_level.txt
dbtlogs/__init__.py
dbtlogs/main.py